koreo/__init__.py
koreo/cache.py
koreo/cel/encoder.py
koreo/cel/evaluation.py
koreo/cel/functions.py
koreo/cel/prepare.py
koreo/cel/structure_extractor.py
koreo/conditions.py
koreo/constants.py
koreo/function_test/prepare.py
koreo/function_test/run.py
koreo/function_test/structure.py
koreo/predicate_helpers.py
koreo/ref_helpers.py
koreo/registry.py
koreo/resource_function/prepare.py
koreo/resource_function/reconcile/__init__.py
koreo/resource_function/reconcile/kind_lookup.py
koreo/resource_function/reconcile/validate.py
koreo/resource_function/structure.py
koreo/resource_template/prepare.py
koreo/resource_template/structure.py
koreo/result.py
koreo/schema/__init__.py
koreo/schema/function-test.yaml
koreo/schema/resource-function.yaml
koreo/schema/resource-template.yaml
koreo/schema/value-function.yaml
koreo/schema/workflow.yaml
koreo/status.py
koreo/value_function/prepare.py
koreo/value_function/reconcile.py
koreo/value_function/structure.py
koreo/workflow/prepare.py
koreo/workflow/reconcile.py
koreo/workflow/structure.py
koreo_core-0.1.17.dist-info/METADATA
koreo_core-0.1.17.dist-info/WHEEL
koreo_core-0.1.17.dist-info/entry_points.txt
koreo_core-0.1.17.dist-info/licenses/LICENSE
koreo_core-0.1.17.dist-info/RECORD
