Metadata-Version: 2.1
Name: koreo-core
Version: 0.1.17
Summary: Type-safe and testable KRM Templates and Workflows.
Author-Email: Robert Kluin <robert.kluin@realkinetic.com>, Eric Larssen <eric.larssen@realkinetic.com>, Tyler Treat <tyler-treat@realkinetic.com>
License: Apache-2.0
Project-URL: Homepage, https://koreo.dev
Requires-Python: >=3.13
Requires-Dist: cel-python==0.3.0
Requires-Dist: PyYAML==6.0.2
Requires-Dist: kr8s==0.20.7
Requires-Dist: fastjsonschema==2.21.1
